CHANGELOG.rst
LICENSE.txt
MANIFEST.in
README.rst
setup.py
bild/__init__.py
bild/bild.py
bild.me_cli.egg-info/PKG-INFO
bild.me_cli.egg-info/SOURCES.txt
bild.me_cli.egg-info/dependency_links.txt
bild.me_cli.egg-info/entry_points.txt
bild.me_cli.egg-info/not-zip-safe
bild.me_cli.egg-info/requires.txt
bild.me_cli.egg-info/top_level.txt