Metadata-Version: 1.0
Name: bild.me-cli
Version: 0.1.0
Summary: CLI tool for bild.me
Home-page: https://github.com/mozillazg/bild.me-cli
Author: mozillazg
Author-email: mozillazg101@gmail.com
License: MIT
Download-URL: https://github.com/mozillazg/bild.me-cli/archive/master.zip
Keywords: bild.me,CLI
Platform: UNKNOWN
Classifier: Development Status :: 5 - Production/Stable
Classifier: Intended Audience :: Developers
Classifier: License :: OSI Approved :: MIT License
Classifier: Operating System :: OS Independent
Classifier: Programming Language :: Python
Classifier: Programming Language :: Python :: 2
Classifier: Programming Language :: Python :: 2.6
Classifier: Programming Language :: Python :: 2.7
Classifier: Programming Language :: Python :: 3
Classifier: Programming Language :: Python :: 3.3
Classifier: Environment :: Console
Classifier: Topic :: Utilities
Classifier: Topic :: Terminals
